CONTRIBUTING.md
MANIFEST.in
README.rst
setup.py
docs/HISTORY.txt
docs/INSTALL.txt
docs/LICENSE.GPL
docs/LICENSE.txt
docs/for-end-users/end-user-documentation.rst
docs/tech-docs/integration-with-zope.rst
docs/tech-docs/images/eea.daviz.dependencies.svg
docs/tech-docs/images/eea.daviz.dependencies.yuml
docs/tech-docs/images/eea.daviz.layers.svg
docs/tech-docs/images/eea.daviz.zope-addFile.png
docs/tech-docs/images/eea.daviz.zope-addedFile.png
docs/tech-docs/images/eea.daviz.zope-daviz-edit.html.png
docs/tech-docs/images/eea.daviz.zope-daviz-view.html.png
eea/__init__.py
eea.daviz.egg-info/PKG-INFO
eea.daviz.egg-info/SOURCES.txt
eea.daviz.egg-info/dependency_links.txt
eea.daviz.egg-info/entry_points.txt
eea.daviz.egg-info/namespace_packages.txt
eea.daviz.egg-info/not-zip-safe
eea.daviz.egg-info/requires.txt
eea.daviz.egg-info/top_level.txt
eea/daviz/CHANGES.txt
eea/daviz/README.txt
eea/daviz/TODO.txt
eea/daviz/__init__.py
eea/daviz/config.py
eea/daviz/configure.zcml
eea/daviz/full.zcml
eea/daviz/interfaces.py
eea/daviz/meta.zcml
eea/daviz/overrides.zcml
eea/daviz/permissions.zcml
eea/daviz/profiles.zcml
eea/daviz/setuphandlers.py
eea/daviz/skins.zcml
eea/daviz/version.txt
eea/daviz/browser/__init__.py
eea/daviz/browser/configure.zcml
eea/daviz/browser/interfaces.py
eea/daviz/browser/app/__init__.py
eea/daviz/browser/app/data.py
eea/daviz/browser/app/daviz.py
eea/daviz/browser/css/datasource.css
eea/daviz/browser/css/spreadsheet.css
eea/daviz/browser/css/tutorials.css
eea/daviz/browser/js/datasource.js
eea/daviz/browser/js/spreadsheet.js
eea/daviz/browser/js/tutorials.js
eea/daviz/browser/js/warnings.js
eea/daviz/browser/zpt/tutorials.pt
eea/daviz/content/__init__.py
eea/daviz/content/configure.zcml
eea/daviz/content/events.py
eea/daviz/content/interfaces.py
eea/daviz/content/presentation.py
eea/daviz/content/schema.py
eea/daviz/content/validators.py
eea/daviz/content/visualization.py
eea/daviz/controlpanel/__init__.py
eea/daviz/controlpanel/configure.zcml
eea/daviz/controlpanel/controlpanel.py
eea/daviz/data/__init__.py
eea/daviz/data/browser.py
eea/daviz/data/configure.zcml
eea/daviz/data/data.py
eea/daviz/data/source.py
eea/daviz/docs/app.txt
eea/daviz/docs/converter.txt
eea/daviz/docs/daviz.doc
eea/daviz/events/__init__.py
