Metadata-Version: 2.1
Name: eea.daviz
Version: 12.2
Summary: EEA DaViz is a plone product which uses Exhibit and Google Charts API to easily create data visualizations based on data from csv/tsv, JSON, SPARQL endpoints and more.
Home-page: https://github.com/collective/eea.daviz
Author: European Environment Agency: IDM2 A-Team
Author-email: eea-edw-a-team-alerts@googlegroups.com
License: GPL
Keywords: EEA Add-ons Plone Zope
Platform: UNKNOWN
Classifier: Framework :: Zope2
Classifier: Framework :: Plone
Classifier: Framework :: Plone :: 4.0
Classifier: Framework :: Plone :: 4.1
Classifier: Framework :: Plone :: 4.2
Classifier: Framework :: Plone :: 4.3
Classifier: Programming Language :: Zope
Classifier: Programming Language :: Python
Classifier: Programming Language :: Python :: 2.7
Classifier: Topic :: Software Development :: Libraries :: Python Modules
Classifier: License :: OSI Approved :: GNU General Public License (GPL)
Provides-Extra: test
Provides-Extra: zope2
Provides-Extra: full
